Workbook

Sheet Cover
A1: ETERNAL LIMITED
A2: Buy-Side Equity DCF Valuation | NSE: ETERNAL | BSE: 543320 | Sector: Consumer Tech (Food Delivery / Quick Commerce)
A3: Prepared: 20-Jul-2026 | Basis: FY25A & FY26A audited/reported consolidated financials, live market data as of 17/19-Jul-2026
A5: SCENARIO SUMMARY
A6: Metric | B6: Bear | C6: Base | D6: Bull
A7: WACC | B7: =DCF!$B$69 -> 0.15844056 | C7: =DCF!$B$69 -> 0.15844056 | D7: =DCF!$B$69 -> 0.15844056
A8: Terminal Growth Rate | B8: =DCF!B74 -> 0.04 | C8: =DCF!C74 -> 0.05 | D8: =DCF!D74 -> 0.06
A9: Enterprise Value (Rs Cr) | B9: =DCF!B78 -> 8019.8848 | C9: =DCF!C78 -> 41164.724 | D9: =DCF!D78 -> 125007.6
A10: Equity Value (Rs Cr) | B10: =DCF!B80 -> 9542.8848 | C10: =DCF!C80 -> 42687.724 | D10: =DCF!D80 -> 126530.6
A11: Implied Price (Rs/share) | B11: =DCF!B82 -> 9.9095377 | C11: =DCF!C82 -> 44.327855 | D11: =DCF!D82 -> 131.39211
A12: CMP (Rs/share) | B12: =DCF!B83 -> 286.6 | C12: =DCF!C83 -> 286.6 | D12: =DCF!D83 -> 286.6
A13: Upside / (Downside) % | B13: =DCF!B84 -> -0.9654238 | C13: =DCF!C84 -> -0.84533198 | D13: =DCF!D84 -> -0.54154882
A15: KEY OBSERVATIONS
A16: 1. Eternal (Zomato/Blinkit/District/Hyperpure) trades at CMP Rs286.6, implying a market cap of ~Rs2.77 lakh Cr and a trailing P/E north of 700x - the market is pricing in a scale of future profitability far beyond current reported earnings.
A17: 2. FY26A reported revenue of Rs54,364 Cr (+169% YoY) is NOT a clean like-for-like comparison to FY25A: it reflects Blinkit's shift to an inventory-led (gross) revenue recognition model plus the consolidation of the acquired Paytm movie-ticketing/District business. Underlying like-for-like growth is materially lower - treat the FY25->FY26 growth rate as a reported-basis data point, not an organic growth signal.
A18: 3. Reported EBIT is negative in both FY25A and FY26A (heavy dark-store D&A), with positive PAT sustained almost entirely by a large other-income/interest line on the company's ~Rs14,000+ Cr cash & investment pile - a structural feature that fades as that pile is deployed into growth capex.
A19: 4. WACC of ~15.8%-15.9% (driven by a high Beta of 1.26 and India's elevated 7.31% Damodaran ERP) sets a demanding hurdle rate; small changes in WACC or TGR swing the implied price materially (see DCF Sheet, Section 6 sensitivity grid).
A20: 5. The Reverse DCF (DCF Sheet, Section 7) backs out the terminal FCFF / steady-state revenue the market is implicitly pricing in at CMP - compare this to the Base-case explicit FY36E figures to judge whether CMP already embeds Bull-case-like assumptions.
A21: 6. Several inputs are flagged [ESTIMATED] because primary filings did not disclose them directly (Capex, Change in NWC, Beta, Kd) - see the Rationale column on the Assumptions sheet for the derivation of every such figure before relying on this model for investment decisions.
A23: COLOR LEGEND
A24: Blue text | B24: Hardcoded input (Assumptions sheet only)
A25: Black text | B25: Formula, calculated within the same sheet
A26: Green text | B26: Link / formula referencing another sheet
A27: Yellow fill | B27: Key output cell (WACC, Implied Price, Upside %, etc.)

Sheet Assumptions
A1: ETERNAL LIMITED (formerly Zomato Ltd) - ASSUMPTIONS
A2: Sector: Consumer Tech (Food Delivery / Quick Commerce) | Buy-Side Equity DCF | All figures Rs Crore unless stated | Consolidated (audited)
A4: 1. Market & Share Data
A5: CMP (Rs/share) | B5: 286.6 | E5: Source: NSE close, 17-Jul-2026 (multiple live feeds cross-checked: IndMoney/Kotak Neo/Google Finance)
A6: Diluted Shares O/S (Cr) | B6: 963 | E6: [ESTIMATED - basis: FY26 PAT Rs366 Cr / diluted EPS Rs0.38 (screener.in) = ~963 Cr diluted shares; basic shares ~919 Cr per equity capital of Rs919 Cr @ FV Re1]
A7: Market Cap (Rs Cr) | B7: =B5*B6 -> 275995.8 | E7: Note: CMP x Diluted Shares
A9: 2. Net Cash Position (Rs Cr) - Net Cash = Cash & Equivalents minus Total Debt
A10: Net Cash - FY25A (Mar-25) | B10: 7221 | E10: Source: Tijori Finance - reported net debt Mar-25 = -Rs7,221 Cr (i.e. net cash of Rs7,221 Cr)
A11: Net Cash - FY26A (Mar-26, latest) | B11: 1523 | E11: Source: Tijori Finance - reported net debt Mar-26 = -Rs1,523 Cr; decline vs FY25 driven by Blinkit dark-store capex, Paytm-ticketing M&A and rising lease-linked borrowings
A13: 3. Actuals - Last 2 Financial Years (Consolidated, Rs Cr)
A14: Line Item | B14: FY25A | C14: FY26A | E14: Source / Note
A15: Revenue from Operations | B15: 20243 | C15: 54364 | E15: Screener.in consolidated P&L (audited annual report FY25; FY26 results filed w/ NSE/BSE 28-Apr-2026). FY26 growth (+169% YoY) driven largely by Blinkit's shift to an inventory-led (gross) revenue model plus consolidation of the acquired Paytm movie-ticketing/District business - NOT purely organic like-for-like growth. [FLAG: revenue basis change FY26]
A16: EBITDA (reported Operating Profit) | B16: 648 | C16: 1208 | E16: Screener.in - Sales less Expenses (pre-D&A, pre-interest), consolidated
A17: EBIT (EBITDA less D&A) | B17: =B16-B18 -> -215 | C17: =C16-C18 -> -389 | E17: Formula: EBITDA - D&A. Negative EBIT despite positive PAT reflects heavy dark-store depreciation offset by large other/interest income (~Rs14,000 Cr cash pile).
A18: D&A | B18: 863 | C18: 1597 | E18: Screener.in P&L - Depreciation & Amortisation
A19: Capex [ESTIMATED] | B19: 931 | C19: 1746 | E19: [ESTIMATED - basis: Capex = Cash from Operations less reported Free Cash Flow (screener.in/Tijori). FY25: 308-(-623)=931; FY26: 632-(-1114)=1746. Primary capex note not separately disclosed in sourced filings.]
A20: Change in Net Working Capital [ESTIMATED] | B20: 1135 | C20: 5994 | E20: [ESTIMATED - basis: NWC = Revenue x Working Capital Days /365 (screener.in ratios: FY24=41 days, FY25=45 days, FY26=57 days); change = current yr NWC - prior yr NWC. Large FY26 jump consistent with Blinkit inventory build-out.]
A21: Effective Tax Rate (reported) | B21: 0.24 | C21: 0.4 | E21: Screener.in P&L - Tax % of PBT. FY26 rate elevated/volatile (deferred-tax movement); statutory rate used for forecast tax shield (see WACC block).
A22: Interest Expense | B22: 154 | C22: 392 | E22: Screener.in P&L - Interest (includes Ind AS 116 lease interest, inflating apparent cost of debt)
A23: Total Debt / Borrowings (period-end) | B23: 2045 | C23: 4592 | E23: Screener.in Balance Sheet - Borrowings, consolidated
A25: 4. WACC Build
A26: Risk-free rate Rf (10Y India G-Sec) | B26: 0.0675 | E26: Source: India 10Y G-Sec yield, mid-Jul 2026 (Trading Economics / DealPlexus; range ~6.72%-6.79% in the two weeks to 17-Jul-2026)
A27: Equity Risk Premium - India (Damodaran) | B27: 0.0731 | E27: Source: Damodaran Country Risk Premium update, July 2026 - India total ERP = 4.17% mature-market ERP + ~3.14% India country risk premium = 7.31%
A28: Beta (Eternal vs Nifty50) | B28: 1.26 | E28: [ESTIMATED - basis: TradingView-reported beta coefficient (methodology/lookback not independently verified); a primary 2Y-weekly regression vs Nifty50 could not be sourced from a data terminal in this research]
A29: Cost of Equity Ke = Rf + Beta x ERP | B29: =B26+B28*B27 -> 0.159606
A30: Interest Expense (FY26A) | B30: =C22 -> 392
A31: Average Debt (FY25-FY26) | B31: =AVERAGE(B23:C23) -> 3318.5
A32: Pre-tax Cost of Debt Kd | B32: =B30/B31 -> 0.11812566 | E32: [ESTIMATED - Kd = FY26 interest expense / average FY25-26 debt; elevated by Ind AS 116 lease interest embedded in reported interest expense and finance-lease borrowings]
A33: Statutory Tax Rate (WACC & NOPAT) | B33: 0.2517 | E33: Source: Indian domestic corporate tax rate incl. surcharge & cess (~25.17%), used given volatility of reported effective rate (24%-40% across FY25-FY26)
A34: After-tax Cost of Debt | B34: =B32*(1-B33) -> 0.088393431
A35: Debt (Market Value proxy, latest) | B35: =C23 -> 4592
A36: Equity (Market Value = Market Cap) | B36: =B7 -> 275995.8
A37: Weight of Debt Wd | B37: =B35/(B35+B36) -> 0.016365644
A38: Weight of Equity We | B38: =B36/(B35+B36) -> 0.98363436
A39: WACC | B39: =B38*B29+B37*B34 -> 0.15844056
A41: 5. Scenario Drivers - Bear / Base / Bull
A42: Driver | B42: Bear | C42: Base | D42: Bull | E42: Rationale / Source
A43: Revenue Growth - Yr1 (FY27E) % | B43: 0.1 | C43: 0.18 | D43: 0.28 | E43: Analyst consensus revenue growth ~23% p.a. blended over next 3 yrs (Simply Wall St, Jul 2026 estimate); Bear/Bull set as a band around Base. [ESTIMATED]
A44: Revenue Growth - Yr10 (FY36E) % | B44: 0.06 | C44: 0.1 | D44: 0.14 | E44: Growth converges toward steady-state as scale matures and base effect normalises. [ESTIMATED]
A45: EBITDA Margin - Yr1 (FY27E) % | B45: 0.03 | C45: 0.04 | D45: 0.05 | E45: Near FY26A margin of ~2.2% (screener.in) with modest near-term improvement as Blinkit losses narrow. [ESTIMATED]
A46: EBITDA Margin - Yr10 (FY36E) % | B46: 0.07 | C46: 0.11 | D46: 0.15 | E46: Global quick-commerce/food-delivery steady-state margins of 8%-15% cited by management/analysts as the path for Blinkit + food delivery combined. [ESTIMATED]
A47: D&A % of Revenue - Yr1 | B47: 0.035 | C47: 0.03 | D47: 0.025 | E47: FY26A D&A/Revenue ~2.9% (screener.in); near-term elevated on dark-store rollout. [ESTIMATED]
A48: D&A % of Revenue - Yr10 | B48: 0.03 | C48: 0.025 | D48: 0.02 | E48: Tapers as fixed-asset base scales sub-linearly with revenue at maturity. [ESTIMATED]
A49: Capex % of Revenue - Yr1 | B49: 0.04 | C49: 0.035 | D49: 0.03 | E49: FY26A implied capex/revenue ~3.2% (derived, see Capex row above); near-term elevated for dark-store/warehouse capex. [ESTIMATED]
A50: Capex % of Revenue - Yr10 | B50: 0.03 | C50: 0.025 | D50: 0.02 | E50: Converges toward D&A run-rate at maturity, per standard terminal-value convention (steady-state capex ~ D&A). [ESTIMATED]
A51: Change in NWC as % of Incremental Revenue | B51: 0.05 | C51: 0.04 | D51: 0.03 | E51: FY26A implied NWC-change/revenue-change ~17.5% (transitional, Blinkit inventory build); assumed to normalise materially lower over the forecast as the model matures. [ESTIMATED]
A52: Terminal Growth Rate (TGR / g) | B52: 0.04 | C52: 0.05 | D52: 0.06 | E52: Set below both the risk-free rate and long-run nominal India GDP growth (~10-11%), per standard Gordon Growth Model convention. [ESTIMATED]
A54: Color Legend
A55: Blue text | B55: Hardcoded input (this sheet only)
A56: Black text | B56: Formula, same sheet
A57: Green text | B57: Link to another sheet
A58: Yellow fill | B58: Key output cell (e.g. WACC)

Sheet DCF
A1: ETERNAL LIMITED (formerly Zomato Ltd) - DCF (Rs Crore, Consolidated)
A2: 10-Year Explicit Forecast + Gordon Growth Terminal Value | FCFF = NOPAT + D&A - Capex - Change in NWC | Scenarios: Bear / Base / Bull
A4: Fiscal Year | B4: Period | C4: FY25A | D4: FY26A | E4: FY27E | F4: FY28E | G4: FY29E | H4: FY30E | I4: FY31E | J4: FY32E | K4: FY33E | L4: FY34E | M4: FY35E | N4: FY36E
A5: Period # (t, for PV) | E5: 1 | F5: 2 | G5: 3 | H5: 4 | I5: 5 | J5: 6 | K5: 7 | L5: 8 | M5: 9 | N5: 10
A7: SECTION 1 - REVENUE BUILD
A8: Revenue Growth % YoY
A9: Bear | E9: =Assumptions!$B$43+(0)/9*(Assumptions!$B$44-Assumptions!$B$43) -> 0.1 | F9: =Assumptions!$B$43+(1)/9*(Assumptions!$B$44-Assumptions!$B$43) -> 0.095555556 | G9: =Assumptions!$B$43+(2)/9*(Assumptions!$B$44-Assumptions!$B$43) -> 0.091111111 | H9: =Assumptions!$B$43+(3)/9*(Assumptions!$B$44-Assumptions!$B$43) -> 0.086666667 | I9: =Assumptions!$B$43+(4)/9*(Assumptions!$B$44-Assumptions!$B$43) -> 0.082222222 | J9: =Assumptions!$B$43+(5)/9*(Assumptions!$B$44-Assumptions!$B$43) -> 0.077777778 | K9: =Assumptions!$B$43+(6)/9*(Assumptions!$B$44-Assumptions!$B$43) -> 0.073333333 | L9: =Assumptions!$B$43+(7)/9*(Assumptions!$B$44-Assumptions!$B$43) -> 0.068888889 | M9: =Assumptions!$B$43+(8)/9*(Assumptions!$B$44-Assumptions!$B$43) -> 0.064444444 | N9: =Assumptions!$B$43+(9)/9*(Assumptions!$B$44-Assumptions!$B$43) -> 0.06
A10: Base | E10: =Assumptions!$C$43+(0)/9*(Assumptions!$C$44-Assumptions!$C$43) -> 0.18 | F10: =Assumptions!$C$43+(1)/9*(Assumptions!$C$44-Assumptions!$C$43) -> 0.17111111 | G10: =Assumptions!$C$43+(2)/9*(Assumptions!$C$44-Assumptions!$C$43) -> 0.16222222 | H10: =Assumptions!$C$43+(3)/9*(Assumptions!$C$44-Assumptions!$C$43) -> 0.15333333 | I10: =Assumptions!$C$43+(4)/9*(Assumptions!$C$44-Assumptions!$C$43) -> 0.14444444 | J10: =Assumptions!$C$43+(5)/9*(Assumptions!$C$44-Assumptions!$C$43) -> 0.13555556 | K10: =Assumptions!$C$43+(6)/9*(Assumptions!$C$44-Assumptions!$C$43) -> 0.12666667 | L10: =Assumptions!$C$43+(7)/9*(Assumptions!$C$44-Assumptions!$C$43) -> 0.11777778 | M10: =Assumptions!$C$43+(8)/9*(Assumptions!$C$44-Assumptions!$C$43) -> 0.10888889 | N10: =Assumptions!$C$43+(9)/9*(Assumptions!$C$44-Assumptions!$C$43) -> 0.1
A11: Bull | E11: =Assumptions!$D$43+(0)/9*(Assumptions!$D$44-Assumptions!$D$43) -> 0.28 | F11: =Assumptions!$D$43+(1)/9*(Assumptions!$D$44-Assumptions!$D$43) -> 0.26444444 | G11: =Assumptions!$D$43+(2)/9*(Assumptions!$D$44-Assumptions!$D$43) -> 0.24888889 | H11: =Assumptions!$D$43+(3)/9*(Assumptions!$D$44-Assumptions!$D$43) -> 0.23333333 | I11: =Assumptions!$D$43+(4)/9*(Assumptions!$D$44-Assumptions!$D$43) -> 0.21777778 | J11: =Assumptions!$D$43+(5)/9*(Assumptions!$D$44-Assumptions!$D$43) -> 0.20222222 | K11: =Assumptions!$D$43+(6)/9*(Assumptions!$D$44-Assumptions!$D$43) -> 0.18666667 | L11: =Assumptions!$D$43+(7)/9*(Assumptions!$D$44-Assumptions!$D$43) -> 0.17111111 | M11: =Assumptions!$D$43+(8)/9*(Assumptions!$D$44-Assumptions!$D$43) -> 0.15555556 | N11: =Assumptions!$D$43+(9)/9*(Assumptions!$D$44-Assumptions!$D$43) -> 0.14
A12: Revenue (Rs Cr)
A13: Bear | C13: =Assumptions!$B$15 -> 20243 | D13: =Assumptions!$C$15 -> 54364 | E13: =D13*(1+E9) -> 59800.4 | F13: =E13*(1+F9) -> 65514.66 | G13: =F13*(1+G9) -> 71483.774 | H13: =G13*(1+H9) -> 77679.034 | I13: =H13*(1+I9) -> 84065.977 | J13: =I13*(1+J9) -> 90604.442 | K13: =J13*(1+K9) -> 97248.768 | L13: =K13*(1+L9) -> 103948.13 | ... N13: =M13*(1+N9) -> 117285.83
A14: Base | C14: =Assumptions!$B$15 -> 20243 | D14: =Assumptions!$C$15 -> 54364 | E14: =D14*(1+E10) -> 64149.52 | F14: =E14*(1+F10) -> 75126.216 | G14: =F14*(1+G10) -> 87313.357 | H14: =G14*(1+H10) -> 100701.41 | I14: =H14*(1+I10) -> 115247.16 | J14: =I14*(1+J10) -> 130869.56 | K14: =J14*(1+K10) -> 147446.37 | L14: =K14*(1+L10) -> 164812.27 | ... N14: =M14*(1+N10) -> 201034.35
A15: Bull | C15: =Assumptions!$B$15 -> 20243 | D15: =Assumptions!$C$15 -> 54364 | E15: =D15*(1+E11) -> 69585.92 | F15: =E15*(1+F11) -> 87987.53 | G15: =F15*(1+G11) -> 109886.65 | H15: =G15*(1+H11) -> 135526.87 | I15: =H15*(1+I11) -> 165041.61 | J15: =I15*(1+J11) -> 198416.69 | K15: =J15*(1+K11) -> 235454.47 | L15: =K15*(1+L11) -> 275743.34 | ... N15: =M15*(1+N11) -> 363245.9
A17: SECTION 2 - EBITDA BRIDGE (Margin x Revenue)
A18: EBITDA Margin %
A19: Bear | E19: =Assumptions!$B$45+(0)/9*(Assumptions!$B$46-Assumptions!$B$45) -> 0.03 | F19: =Assumptions!$B$45+(1)/9*(Assumptions!$B$46-Assumptions!$B$45) -> 0.034444444 | G19: =Assumptions!$B$45+(2)/9*(Assumptions!$B$46-Assumptions!$B$45) -> 0.038888889 | H19: =Assumptions!$B$45+(3)/9*(Assumptions!$B$46-Assumptions!$B$45) -> 0.043333333 | I19: =Assumptions!$B$45+(4)/9*(Assumptions!$B$46-Assumptions!$B$45) -> 0.047777778 | J19: =Assumptions!$B$45+(5)/9*(Assumptions!$B$46-Assumptions!$B$45) -> 0.052222222 | K19: =Assumptions!$B$45+(6)/9*(Assumptions!$B$46-Assumptions!$B$45) -> 0.056666667 | L19: =Assumptions!$B$45+(7)/9*(Assumptions!$B$46-Assumptions!$B$45) -> 0.061111111 | M19: =Assumptions!$B$45+(8)/9*(Assumptions!$B$46-Assumptions!$B$45) -> 0.065555556 | N19: =Assumptions!$B$45+(9)/9*(Assumptions!$B$46-Assumptions!$B$45) -> 0.07
A20: Base | E20: =Assumptions!$C$45+(0)/9*(Assumptions!$C$46-Assumptions!$C$45) -> 0.04 | F20: =Assumptions!$C$45+(1)/9*(Assumptions!$C$46-Assumptions!$C$45) -> 0.047777778 | G20: =Assumptions!$C$45+(2)/9*(Assumptions!$C$46-Assumptions!$C$45) -> 0.055555556 | H20: =Assumptions!$C$45+(3)/9*(Assumptions!$C$46-Assumptions!$C$45) -> 0.063333333 | I20: =Assumptions!$C$45+(4)/9*(Assumptions!$C$46-Assumptions!$C$45) -> 0.071111111 | J20: =Assumptions!$C$45+(5)/9*(Assumptions!$C$46-Assumptions!$C$45) -> 0.078888889 | K20: =Assumptions!$C$45+(6)/9*(Assumptions!$C$46-Assumptions!$C$45) -> 0.086666667 | L20: =Assumptions!$C$45+(7)/9*(Assumptions!$C$46-Assumptions!$C$45) -> 0.094444444 | M20: =Assumptions!$C$45+(8)/9*(Assumptions!$C$46-Assumptions!$C$45) -> 0.10222222 | N20: =Assumptions!$C$45+(9)/9*(Assumptions!$C$46-Assumptions!$C$45) -> 0.11
A21: Bull | E21: =Assumptions!$D$45+(0)/9*(Assumptions!$D$46-Assumptions!$D$45) -> 0.05 | F21: =Assumptions!$D$45+(1)/9*(Assumptions!$D$46-Assumptions!$D$45) -> 0.061111111 | G21: =Assumptions!$D$45+(2)/9*(Assumptions!$D$46-Assumptions!$D$45) -> 0.072222222 | H21: =Assumptions!$D$45+(3)/9*(Assumptions!$D$46-Assumptions!$D$45) -> 0.083333333 | I21: =Assumptions!$D$45+(4)/9*(Assumptions!$D$46-Assumptions!$D$45) -> 0.094444444 | J21: =Assumptions!$D$45+(5)/9*(Assumptions!$D$46-Assumptions!$D$45) -> 0.10555556 | K21: =Assumptions!$D$45+(6)/9*(Assumptions!$D$46-Assumptions!$D$45) -> 0.11666667 | L21: =Assumptions!$D$45+(7)/9*(Assumptions!$D$46-Assumptions!$D$45) -> 0.12777778 | M21: =Assumptions!$D$45+(8)/9*(Assumptions!$D$46-Assumptions!$D$45) -> 0.13888889 | N21: =Assumptions!$D$45+(9)/9*(Assumptions!$D$46-Assumptions!$D$45) -> 0.15
A22: EBITDA (Rs Cr)
A23: Bear | C23: =Assumptions!$B$16 -> 648 | D23: =Assumptions!$C$16 -> 1208 | E23: =E13*E19 -> 1794.012 | F23: =F13*F19 -> 2256.6161 | G23: =G13*G19 -> 2779.9245 | H23: =H13*H19 -> 3366.0915 | I23: =I13*I19 -> 4016.4856 | J23: =J13*J19 -> 4731.5653 | K23: =K13*K19 -> 5510.7635 | L23: =L13*L19 -> 6352.3856 | ... N23: =N13*N19 -> 8210.0079
A24: Base | C24: =Assumptions!$B$16 -> 648 | D24: =Assumptions!$C$16 -> 1208 | E24: =E14*E20 -> 2565.9808 | F24: =F14*F20 -> 3589.3636 | G24: =G14*G20 -> 4850.7421 | H24: =H14*H20 -> 6377.7557 | I24: =I14*I20 -> 8195.3539 | J24: =J14*J20 -> 10324.154 | K24: =K14*K20 -> 12778.685 | L24: =L14*L20 -> 15565.604 | ... N24: =N14*N20 -> 22113.778
A25: Bull | C25: =Assumptions!$B$16 -> 648 | D25: =Assumptions!$C$16 -> 1208 | E25: =E15*E21 -> 3479.296 | F25: =F15*F21 -> 5377.0157 | G25: =G15*G21 -> 7936.2579 | H25: =H15*H21 -> 11293.906 | I25: =I15*I21 -> 15587.263 | J25: =J15*J21 -> 20943.984 | K25: =K15*K21 -> 27469.688 | L25: =L15*L21 -> 35233.872 | ... N25: =N15*N21 -> 54486.885
A27: SECTION 3 - FCFF WATERFALL (EBITDA -> D&A -> EBIT -> Tax -> NOPAT -> +D&A -> -Capex -> -dNWC -> FCFF)
A28: Bear Case
A29: EBITDA | C29: =C23 -> 648 | D29: =D23 -> 1208 | E29: =E23 -> 1794.012 | F29: =F23 -> 2256.6161 | G29: =G23 -> 2779.9245 | H29: =H23 -> 3366.0915 | I29: =I23 -> 4016.4856 | J29: =J23 -> 4731.5653 | ... N29: =N23 -> 8210.0079
A30: (-) D&A | C30: =Assumptions!$B$18 -> 863 | D30: =Assumptions!$C$18 -> 1597 | E30: =E13*(Assumptions!$B$47+(0)/9*(Assumptions!$B$48-Assumptions!$B$47)) -> 2093.014 | F30: =F13*(Assumptions!$B$47+(1)/9*(Assumptions!$B$48-Assumptions!$B$47)) -> 2256.6161 | G30: =G13*(Assumptions!$B$47+(2)/9*(Assumptions!$B$48-Assumptions!$B$47)) -> 2422.5057 | H30: =H13*(Assumptions!$B$47+(3)/9*(Assumptions!$B$48-Assumptions!$B$47)) -> 2589.3011 | I30: =I13*(Assumptions!$B$47+(4)/9*(Assumptions!$B$48-Assumptions!$B$47)) -> 2755.4959 | J30: =J13*(Assumptions!$B$47+(5)/9*(Assumptions!$B$48-Assumptions!$B$47)) -> 2919.4765 | K30: =K13*(Assumptions!$B$47+(6)/9*(Assumptions!$B$48-Assumptions!$B$47)) -> 3079.5443 | L30: =L13*(Assumptions!$B$47+(7)/9*(Assumptions!$B$48-Assumptions!$B$47)) -> 3233.9417 | M30: =M13*(Assumptions!$B$47+(8)/9*(Assumptions!$B$48-Assumptions!$B$47)) -> 3380.8808 | N30: =N13*(Assumptions!$B$47+(9)/9*(Assumptions!$B$48-Assumptions!$B$47)) -> 3518.5748
A31: EBIT | C31: =C29-C30 -> -215 | D31: =D29-D30 -> -389 | E31: =E29-E30 -> -299.002 | F31: =F29-F30 -> 0 | G31: =G29-G30 -> 357.41887 | H31: =H29-H30 -> 776.79034 | I31: =I29-I30 -> 1260.9897 | J31: =J29-J30 -> 1812.0888 | ... N31: =N29-N30 -> 4691.4331
A32: (-) Tax @ statutory rate | E32: =MAX(E31,0)*Assumptions!$B$33 -> 0 | F32: =MAX(F31,0)*Assumptions!$B$33 -> 0 | G32: =MAX(G31,0)*Assumptions!$B$33 -> 89.96233 | H32: =MAX(H31,0)*Assumptions!$B$33 -> 195.51813 | I32: =MAX(I31,0)*Assumptions!$B$33 -> 317.3911 | J32: =MAX(J31,0)*Assumptions!$B$33 -> 456.10276 | K32: =MAX(K31,0)*Assumptions!$B$33 -> 611.93787 | L32: =MAX(L31,0)*Assumptions!$B$33 -> 784.91231 | ... N32: =MAX(N31,0)*Assumptions!$B$33 -> 1180.8337
A33: NOPAT | E33: =E31-E32 -> -299.002 | F33: =F31-F32 -> 0 | G33: =G31-G32 -> 267.45654 | H33: =H31-H32 -> 581.27221 | I33: =I31-I32 -> 943.59856 | J33: =J31-J32 -> 1355.9861 | K33: =K31-K32 -> 1819.2813 | L33: =L31-L32 -> 2333.5315 | ... N33: =N31-N32 -> 3510.5994
A34: (+) D&A | E34: =E30 -> 2093.014 | F34: =F30 -> 2256.6161 | G34: =G30 -> 2422.5057 | H34: =H30 -> 2589.3011 | I34: =I30 -> 2755.4959 | J34: =J30 -> 2919.4765 | K34: =K30 -> 3079.5443 | L34: =L30 -> 3233.9417 | ... N34: =N30 -> 3518.5748
A35: (-) Capex | E35: =E13*(Assumptions!$B$49+(0)/9*(Assumptions!$B$50-Assumptions!$B$49)) -> 2392.016 | F35: =F13*(Assumptions!$B$49+(1)/9*(Assumptions!$B$50-Assumptions!$B$49)) -> 2547.7924 | G35: =G13*(Assumptions!$B$49+(2)/9*(Assumptions!$B$50-Assumptions!$B$49)) -> 2700.4981 | H35: =H13*(Assumptions!$B$49+(3)/9*(Assumptions!$B$50-Assumptions!$B$49)) -> 2848.2313 | I35: =I13*(Assumptions!$B$49+(4)/9*(Assumptions!$B$50-Assumptions!$B$49)) -> 2989.0125 | J35: =J13*(Assumptions!$B$49+(5)/9*(Assumptions!$B$50-Assumptions!$B$49)) -> 3120.8197 | K35: =K13*(Assumptions!$B$49+(6)/9*(Assumptions!$B$50-Assumptions!$B$49)) -> 3241.6256 | L35: =L13*(Assumptions!$B$49+(7)/9*(Assumptions!$B$50-Assumptions!$B$49)) -> 3349.4397 | M35: =M13*(Assumptions!$B$49+(8)/9*(Assumptions!$B$50-Assumptions!$B$49)) -> 3442.3513 | N35: =N13*(Assumptions!$B$49+(9)/9*(Assumptions!$B$50-Assumptions!$B$49)) -> 3518.5748
A36: (-) Change in NWC | E36: =(E13-D13)*Assumptions!$B$51 -> 271.82 | F36: =(F13-E13)*Assumptions!$B$51 -> 285.71302 | G36: =(G13-F13)*Assumptions!$B$51 -> 298.45568 | H36: =(H13-G13)*Assumptions!$B$51 -> 309.76302 | I36: =(I13-H13)*Assumptions!$B$51 -> 319.34714 | J36: =(J13-I13)*Assumptions!$B$51 -> 326.92324 | K36: =(K13-J13)*Assumptions!$B$51 -> 332.21629 | L36: =(L13-K13)*Assumptions!$B$51 -> 334.96798 | ... N36: =(N13-M13)*Assumptions!$B$51 -> 331.94102
A37: FCFF | E37: =E33+E34-E35-E36 -> -869.824 | F37: =F33+F34-F35-F36 -> -576.88929 | G37: =G33+G34-G35-G36 -> -308.99159 | H37: =H33+H34-H35-H36 -> 12.579079 | I37: =I33+I34-I35-I36 -> 390.73482 | J37: =J33+J34-J35-J36 -> 827.71963 | K37: =K33+K34-K35-K36 -> 1324.9838 | L37: =L33+L34-L35-L36 -> 1883.0656 | ... N37: =N33+N34-N35-N36 -> 3178.6584
A39: Base Case
A40: EBITDA | C40: =C24 -> 648 | D40: =D24 -> 1208 | E40: =E24 -> 2565.9808 | F40: =F24 -> 3589.3636 | G40: =G24 -> 4850.7421 | H40: =H24 -> 6377.7557 | I40: =I24 -> 8195.3539 | J40: =J24 -> 10324.154 | ... N40: =N24 -> 22113.778
A41: (-) D&A | C41: =Assumptions!$B$18 -> 863 | D41: =Assumptions!$C$18 -> 1597 | E41: =E14*(Assumptions!$C$47+(0)/9*(Assumptions!$C$48-Assumptions!$C$47)) -> 1924.4856 | F41: =F14*(Assumptions!$C$47+(1)/9*(Assumptions!$C$48-Assumptions!$C$47)) -> 2212.0497 | G41: =G14*(Assumptions!$C$47+(2)/9*(Assumptions!$C$48-Assumptions!$C$47)) -> 2522.3859 | H41: =H14*(Assumptions!$C$47+(3)/9*(Assumptions!$C$48-Assumptions!$C$47)) -> 2853.2065 | I41: =I14*(Assumptions!$C$47+(4)/9*(Assumptions!$C$48-Assumptions!$C$47)) -> 3201.3101 | J41: =J14*(Assumptions!$C$47+(5)/9*(Assumptions!$C$48-Assumptions!$C$47)) -> 3562.5602 | K41: =K14*(Assumptions!$C$47+(6)/9*(Assumptions!$C$48-Assumptions!$C$47)) -> 3931.9031 | L41: =L14*(Assumptions!$C$47+(7)/9*(Assumptions!$C$48-Assumptions!$C$47)) -> 4303.4316 | M41: =M14*(Assumptions!$C$47+(8)/9*(Assumptions!$C$48-Assumptions!$C$47)) -> 4670.495 | N41: =N14*(Assumptions!$C$47+(9)/9*(Assumptions!$C$48-Assumptions!$C$47)) -> 5025.8587
A42: EBIT | C42: =C40-C41 -> -215 | D42: =D40-D41 -> -389 | E42: =E40-E41 -> 641.4952 | F42: =F40-F41 -> 1377.314 | G42: =G40-G41 -> 2328.3562 | H42: =H40-H41 -> 3524.5492 | I42: =I40-I41 -> 4994.0438 | J42: =J40-J41 -> 6761.5938 | ... N42: =N40-N41 -> 17087.92
A43: (-) Tax @ statutory rate | E43: =MAX(E42,0)*Assumptions!$B$33 -> 161.46434 | F43: =MAX(F42,0)*Assumptions!$B$33 -> 346.66992 | G43: =MAX(G42,0)*Assumptions!$B$33 -> 586.04725 | H43: =MAX(H42,0)*Assumptions!$B$33 -> 887.12903 | I43: =MAX(I42,0)*Assumptions!$B$33 -> 1257.0008 | J43: =MAX(J42,0)*Assumptions!$B$33 -> 1701.8932 | K43: =MAX(K42,0)*Assumptions!$B$33 -> 2226.735 | L43: =MAX(L42,0)*Assumptions!$B$33 -> 2834.6887 | ... N43: =MAX(N42,0)*Assumptions!$B$33 -> 4301.0294
A44: NOPAT | E44: =E42-E43 -> 480.03086 | F44: =F42-F43 -> 1030.644 | G44: =G42-G43 -> 1742.3089 | H44: =H42-H43 -> 2637.4202 | I44: =I42-I43 -> 3737.043 | J44: =J42-J43 -> 5059.7006 | K44: =K42-K43 -> 6620.047 | L44: =L42-L43 -> 8427.4833 | ... N44: =N42-N43 -> 12786.89
A45: (+) D&A | E45: =E41 -> 1924.4856 | F45: =F41 -> 2212.0497 | G45: =G41 -> 2522.3859 | H45: =H41 -> 2853.2065 | I45: =I41 -> 3201.3101 | J45: =J41 -> 3562.5602 | K45: =K41 -> 3931.9031 | L45: =L41 -> 4303.4316 | ... N45: =N41 -> 5025.8587
A46: (-) Capex | E46: =E14*(Assumptions!$C$49+(0)/9*(Assumptions!$C$50-Assumptions!$C$49)) -> 2245.2332 | F46: =F14*(Assumptions!$C$49+(1)/9*(Assumptions!$C$50-Assumptions!$C$49)) -> 2545.944 | G46: =G14*(Assumptions!$C$49+(2)/9*(Assumptions!$C$50-Assumptions!$C$49)) -> 2861.9378 | H46: =H14*(Assumptions!$C$49+(3)/9*(Assumptions!$C$50-Assumptions!$C$49)) -> 3188.8778 | I46: =I14*(Assumptions!$C$49+(4)/9*(Assumptions!$C$50-Assumptions!$C$49)) -> 3521.4411 | J46: =J14*(Assumptions!$C$49+(5)/9*(Assumptions!$C$50-Assumptions!$C$49)) -> 3853.3814 | K46: =K14*(Assumptions!$C$49+(6)/9*(Assumptions!$C$50-Assumptions!$C$49)) -> 4177.6471 | L46: =L14*(Assumptions!$C$49+(7)/9*(Assumptions!$C$50-Assumptions!$C$49)) -> 4486.5563 | M46: =M14*(Assumptions!$C$49+(8)/9*(Assumptions!$C$50-Assumptions!$C$49)) -> 4772.0275 | N46: =N14*(Assumptions!$C$49+(9)/9*(Assumptions!$C$50-Assumptions!$C$49)) -> 5025.8587
A47: (-) Change in NWC | E47: =(E14-D14)*Assumptions!$C$51 -> 391.4208 | F47: =(F14-E14)*Assumptions!$C$51 -> 439.06783 | G47: =(G14-F14)*Assumptions!$C$51 -> 487.48567 | H47: =(H14-G14)*Assumptions!$C$51 -> 535.52192 | I47: =(I14-H14)*Assumptions!$C$51 -> 581.83034 | J47: =(J14-I14)*Assumptions!$C$51 -> 624.89573 | K47: =(K14-J14)*Assumptions!$C$51 -> 663.07242 | L47: =(L14-K14)*Assumptions!$C$51 -> 694.63622 | ... N47: =(N14-M14)*Assumptions!$C$51 -> 731.034
A48: FCFF | E48: =E44+E45-E46-E47 -> -232.13754 | F48: =F44+F45-F46-F47 -> 257.68191 | G48: =G44+G45-G46-G47 -> 915.27133 | H48: =H44+H45-H46-H47 -> 1766.2269 | I48: =I44+I45-I46-I47 -> 2835.0816 | J48: =J44+J45-J46-J47 -> 4143.9837 | K48: =K44+K45-K46-K47 -> 5711.2307 | L48: =L44+L45-L46-L47 -> 7549.7224 | ... N48: =N44+N45-N46-N47 -> 12055.856
A50: Bull Case
A51: EBITDA | C51: =C25 -> 648 | D51: =D25 -> 1208 | E51: =E25 -> 3479.296 | F51: =F25 -> 5377.0157 | G51: =G25 -> 7936.2579 | H51: =H25 -> 11293.906 | I51: =I25 -> 15587.263 | J51: =J25 -> 20943.984 | ... N51: =N25 -> 54486.885
A52: (-) D&A | C52: =Assumptions!$B$18 -> 863 | D52: =Assumptions!$C$18 -> 1597 | E52: =E15*(Assumptions!$D$47+(0)/9*(Assumptions!$D$48-Assumptions!$D$47)) -> 1739.648 | F52: =F15*(Assumptions!$D$47+(1)/9*(Assumptions!$D$48-Assumptions!$D$47)) -> 2150.8063 | G52: =G15*(Assumptions!$D$47+(2)/9*(Assumptions!$D$48-Assumptions!$D$47)) -> 2625.0699 | H52: =H15*(Assumptions!$D$47+(3)/9*(Assumptions!$D$48-Assumptions!$D$47)) -> 3162.2936 | I52: =I15*(Assumptions!$D$47+(4)/9*(Assumptions!$D$48-Assumptions!$D$47)) -> 3759.281 | J52: =J15*(Assumptions!$D$47+(5)/9*(Assumptions!$D$48-Assumptions!$D$47)) -> 4409.2597 | K52: =K15*(Assumptions!$D$47+(6)/9*(Assumptions!$D$48-Assumptions!$D$47)) -> 5101.5135 | L52: =L15*(Assumptions!$D$47+(7)/9*(Assumptions!$D$48-Assumptions!$D$47)) -> 5821.2484 | M52: =M15*(Assumptions!$D$47+(8)/9*(Assumptions!$D$48-Assumptions!$D$47)) -> 6549.7555 | N52: =N15*(Assumptions!$D$47+(9)/9*(Assumptions!$D$48-Assumptions!$D$47)) -> 7264.918
A53: EBIT | C53: =C51-C52 -> -215 | D53: =D51-D52 -> -389 | E53: =E51-E52 -> 1739.648 | F53: =F51-F52 -> 3226.2094 | G53: =G51-G52 -> 5311.188 | H53: =H51-H52 -> 8131.612 | I53: =I51-I52 -> 11827.982 | J53: =J51-J52 -> 16534.724 | ... N53: =N51-N52 -> 47221.967
A54: (-) Tax @ statutory rate | E54: =MAX(E53,0)*Assumptions!$B$33 -> 437.8694 | F54: =MAX(F53,0)*Assumptions!$B$33 -> 812.03691 | G54: =MAX(G53,0)*Assumptions!$B$33 -> 1336.826 | H54: =MAX(H53,0)*Assumptions!$B$33 -> 2046.7267 | I54: =MAX(I53,0)*Assumptions!$B$33 -> 2977.103 | J54: =MAX(J53,0)*Assumptions!$B$33 -> 4161.79 | K54: =MAX(K53,0)*Assumptions!$B$33 -> 5630.0695 | L54: =MAX(L53,0)*Assumptions!$B$33 -> 7403.1573 | ... N54: =MAX(N53,0)*Assumptions!$B$33 -> 11885.769
A55: NOPAT | E55: =E53-E54 -> 1301.7786 | F55: =F53-F54 -> 2414.1725 | G55: =G53-G54 -> 3974.362 | H55: =H53-H54 -> 6084.8853 | I55: =I53-I54 -> 8850.8788 | J55: =J53-J54 -> 12372.934 | K55: =K53-K54 -> 16738.105 | L55: =L53-L54 -> 22009.466 | ... N55: =N53-N54 -> 35336.198
A56: (+) D&A | E56: =E52 -> 1739.648 | F56: =F52 -> 2150.8063 | G56: =G52 -> 2625.0699 | H56: =H52 -> 3162.2936 | I56: =I52 -> 3759.281 | J56: =J52 -> 4409.2597 | K56: =K52 -> 5101.5135 | L56: =L52 -> 5821.2484 | ... N56: =N52 -> 7264.918
A57: (-) Capex | E57: =E15*(Assumptions!$D$49+(0)/9*(Assumptions!$D$50-Assumptions!$D$49)) -> 2087.5776 | F57: =F15*(Assumptions!$D$49+(1)/9*(Assumptions!$D$50-Assumptions!$D$49)) -> 2541.862 | G57: =G15*(Assumptions!$D$49+(2)/9*(Assumptions!$D$50-Assumptions!$D$49)) -> 3052.4069 | H57: =H15*(Assumptions!$D$49+(3)/9*(Assumptions!$D$50-Assumptions!$D$49)) -> 3614.0498 | I57: =I15*(Assumptions!$D$49+(4)/9*(Assumptions!$D$50-Assumptions!$D$49)) -> 4217.7299 | J57: =J15*(Assumptions!$D$49+(5)/9*(Assumptions!$D$50-Assumptions!$D$49)) -> 4850.1857 | K57: =K15*(Assumptions!$D$49+(6)/9*(Assumptions!$D$50-Assumptions!$D$49)) -> 5493.9376 | L57: =L15*(Assumptions!$D$49+(7)/9*(Assumptions!$D$50-Assumptions!$D$49)) -> 6127.6299 | M57: =M15*(Assumptions!$D$49+(8)/9*(Assumptions!$D$50-Assumptions!$D$49)) -> 6726.7759 | N57: =N15*(Assumptions!$D$49+(9)/9*(Assumptions!$D$50-Assumptions!$D$49)) -> 7264.918
A58: (-) Change in NWC | E58: =(E15-D15)*Assumptions!$D$51 -> 456.6576 | F58: =(F15-E15)*Assumptions!$D$51 -> 552.0483 | G58: =(G15-F15)*Assumptions!$D$51 -> 656.97356 | H58: =(H15-G15)*Assumptions!$D$51 -> 769.20654 | I58: =(I15-H15)*Assumptions!$D$51 -> 885.44219 | J58: =(J15-I15)*Assumptions!$D$51 -> 1001.2524 | K58: =(K15-J15)*Assumptions!$D$51 -> 1111.1334 | L58: =(L15-K15)*Assumptions!$D$51 -> 1208.6663 | ... N58: =(N15-M15)*Assumptions!$D$51 -> 1338.2744
A59: FCFF | E59: =E55+E56-E57-E58 -> 497.1914 | F59: =F55+F56-F57-F58 -> 1471.0685 | G59: =G55+G56-G57-G58 -> 2890.0515 | H59: =H55+H56-H57-H58 -> 4863.9225 | I59: =I55+I56-I57-I58 -> 7506.9877 | J59: =J55+J56-J57-J58 -> 10930.756 | K59: =K55+K56-K57-K58 -> 15234.547 | L59: =L55+L56-L57-L58 -> 20494.418 | ... N59: =N55+N56-N57-N58 -> 33997.923
A61: SECTION 4 - WACC SUMMARY (linked from Assumptions)
A62: Risk-free Rate (Rf) | B62: =Assumptions!$B$26 -> 0.0675
A63: Equity Risk Premium (ERP) | B63: =Assumptions!$B$27 -> 0.0731
A64: Beta | B64: =Assumptions!$B$28 -> 1.26
A65: Cost of Equity (Ke) | B65: =Assumptions!$B$29 -> 0.159606
A66: After-tax Cost of Debt (Kd) | B66: =Assumptions!$B$34 -> 0.088393431
A67: Weight of Equity (We) | B67: =Assumptions!$B$38 -> 0.98363436
A68: Weight of Debt (Wd) | B68: =Assumptions!$B$37 -> 0.016365644
A69: WACC | B69: =Assumptions!$B$39 -> 0.15844056
A71: SECTION 5 - VALUATION TABLE
A72: Metric | B72: Bear | C72: Base | D72: Bull
A73: Terminal FCFF (FY36E, Rs Cr) | B73: =N37 -> 3178.6584 | C73: =N48 -> 12055.856 | D73: =N59 -> 33997.923
A74: Terminal Growth Rate (g) | B74: =Assumptions!$B$52 -> 0.04 | C74: =Assumptions!$C$52 -> 0.05 | D74: =Assumptions!$D$52 -> 0.06
A75: Terminal Value TV = FCFFn(1+g)/(WACC-g) | B75: =B73*(1+B74)/($B$69-B74) -> 27911.086 | C75: =C73*(1+C74)/($B$69-C74) -> 116733.53 | D75: =D73*(1+D74)/($B$69-D74) -> 366086.89
A76: PV (Terminal Value) | B76: =B75/(1+$B$69)^10 -> 6412.6744 | C76: =C75/(1+$B$69)^10 -> 26819.956 | D76: =D75/(1+$B$69)^10 -> 84109.805
A77: PV (Sum of 10Y Explicit FCFFs) | B77: =SUMPRODUCT(E37:N37,1/(1+$B$69)^(E5:N5)) -> 1607.2104 | C77: =SUMPRODUCT(E48:N48,1/(1+$B$69)^(E5:N5)) -> 14344.769 | D77: =SUMPRODUCT(E59:N59,1/(1+$B$69)^(E5:N5)) -> 40897.796
A78: Enterprise Value (EV) | B78: =B77+B76 -> 8019.8848 | C78: =C77+C76 -> 41164.724 | D78: =D77+D76 -> 125007.6
A79: (+) Net Cash (FY26A, latest) | B79: =Assumptions!$B$11 -> 1523 | C79: =Assumptions!$B$11 -> 1523 | D79: =Assumptions!$B$11 -> 1523
A80: Equity Value | B80: =B78+B79 -> 9542.8848 | C80: =C78+C79 -> 42687.724 | D80: =D78+D79 -> 126530.6
A81: Diluted Shares O/S (Cr) | B81: =Assumptions!$B$6 -> 963 | C81: =Assumptions!$B$6 -> 963 | D81: =Assumptions!$B$6 -> 963
A82: Implied Price per Share (Rs) | B82: =B80/B81 -> 9.9095377 | C82: =C80/C81 -> 44.327855 | D82: =D80/D81 -> 131.39211
A83: CMP (Rs) | B83: =Assumptions!$B$5 -> 286.6 | C83: =Assumptions!$B$5 -> 286.6 | D83: =Assumptions!$B$5 -> 286.6
A84: Upside / (Downside) % | B84: =B82/B83-1 -> -0.9654238 | C84: =C82/C83-1 -> -0.84533198 | D84: =D82/D83-1 -> -0.54154882
A86: SECTION 6 - SENSITIVITY: Implied Price (Rs) - WACC (rows) x Terminal Growth Rate (cols) - Base Case FCFFs, GGM throughout
A87: (WACC and TGR flex independently of the Base-case scenario driver values above; Base-case FCFF stream held fixed, PV recomputed for each WACC)
A88: WACC \ TGR | C88: =$C$74+(-0.02) -> 0.03 | D88: =$C$74+(-0.01) -> 0.04 | E88: =$C$74+(0) -> 0.05 | F88: =$C$74+(0.01) -> 0.06 | G88: =$C$74+(0.02) -> 0.07
B89: =$B$69+(-0.02) -> 0.13844056 | C89: =((SUMPRODUCT(E48:N48,1/(1+$B89)^(E5:N5)))+((N48*(1+C$88)/($B89-C$88))/(1+$B89)^10)+Assumptions!$B$11)/Assumptions!$B$6 -> 51.065333 | D89: =((SUMPRODUCT(E48:N48,1/(1+$B89)^(E5:N5)))+((N48*(1+D$88)/($B89-D$88))/(1+$B89)^10)+Assumptions!$B$11)/Assumptions!$B$6 -> 54.71634 | E89: =((SUMPRODUCT(E48:N48,1/(1+$B89)^(E5:N5)))+((N48*(1+E$88)/($B89-E$88))/(1+$B89)^10)+Assumptions!$B$11)/Assumptions!$B$6 -> 59.192988 | F89: =((SUMPRODUCT(E48:N48,1/(1+$B89)^(E5:N5)))+((N48*(1+F$88)/($B89-F$88))/(1+$B89)^10)+Assumptions!$B$11)/Assumptions!$B$6 -> 64.811048 | G89: =((SUMPRODUCT(E48:N48,1/(1+$B89)^(E5:N5)))+((N48*(1+G$88)/($B89-G$88))/(1+$B89)^10)+Assumptions!$B$11)/Assumptions!$B$6 -> 72.070842
B90: =$B$69+(-0.01) -> 0.14844056 | C90: =((SUMPRODUCT(E48:N48,1/(1+$B90)^(E5:N5)))+((N48*(1+C$88)/($B90-C$88))/(1+$B90)^10)+Assumptions!$B$11)/Assumptions!$B$6 -> 44.750849 | D90: =((SUMPRODUCT(E48:N48,1/(1+$B90)^(E5:N5)))+((N48*(1+D$88)/($B90-D$88))/(1+$B90)^10)+Assumptions!$B$11)/Assumptions!$B$6 -> 47.555656 | E90: =((SUMPRODUCT(E48:N48,1/(1+$B90)^(E5:N5)))+((N48*(1+E$88)/($B90-E$88))/(1+$B90)^10)+Assumptions!$B$11)/Assumptions!$B$6 -> 50.93031 | F90: =((SUMPRODUCT(E48:N48,1/(1+$B90)^(E5:N5)))+((N48*(1+F$88)/($B90-F$88))/(1+$B90)^10)+Assumptions!$B$11)/Assumptions!$B$6 -> 55.06811 | G90: =((SUMPRODUCT(E48:N48,1/(1+$B90)^(E5:N5)))+((N48*(1+G$88)/($B90-G$88))/(1+$B90)^10)+Assumptions!$B$11)/Assumptions!$B$6 -> 60.260925
B91: =$B$69+(0) -> 0.15844056 | C91: =((SUMPRODUCT(E48:N48,1/(1+$B91)^(E5:N5)))+((N48*(1+C$88)/($B91-C$88))/(1+$B91)^10)+Assumptions!$B$11)/Assumptions!$B$6 -> 39.543273 | D91: =((SUMPRODUCT(E48:N48,1/(1+$B91)^(E5:N5)))+((N48*(1+D$88)/($B91-D$88))/(1+$B91)^10)+Assumptions!$B$11)/Assumptions!$B$6 -> 41.733581 | E91: =((SUMPRODUCT(E48:N48,1/(1+$B91)^(E5:N5)))+((N48*(1+E$88)/($B91-E$88))/(1+$B91)^10)+Assumptions!$B$11)/Assumptions!$B$6 -> 44.327855 | F91: =((SUMPRODUCT(E48:N48,1/(1+$B91)^(E5:N5)))+((N48*(1+F$88)/($B91-F$88))/(1+$B91)^10)+Assumptions!$B$11)/Assumptions!$B$6 -> 47.449203 | G91: =((SUMPRODUCT(E48:N48,1/(1+$B91)^(E5:N5)))+((N48*(1+G$88)/($B91-G$88))/(1+$B91)^10)+Assumptions!$B$11)/Assumptions!$B$6 -> 51.276414
B92: =$B$69+(0.01) -> 0.16844056 | C92: =((SUMPRODUCT(E48:N48,1/(1+$B92)^(E5:N5)))+((N48*(1+C$88)/($B92-C$88))/(1+$B92)^10)+Assumptions!$B$11)/Assumptions!$B$6 -> 35.194094 | D92: =((SUMPRODUCT(E48:N48,1/(1+$B92)^(E5:N5)))+((N48*(1+D$88)/($B92-D$88))/(1+$B92)^10)+Assumptions!$B$11)/Assumptions!$B$6 -> 36.928484 | E92: =((SUMPRODUCT(E48:N48,1/(1+$B92)^(E5:N5)))+((N48*(1+E$88)/($B92-E$88))/(1+$B92)^10)+Assumptions!$B$11)/Assumptions!$B$6 -> 38.955744 | F92: =((SUMPRODUCT(E48:N48,1/(1+$B92)^(E5:N5)))+((N48*(1+F$88)/($B92-F$88))/(1+$B92)^10)+Assumptions!$B$11)/Assumptions!$B$6 -> 41.356897 | G92: =((SUMPRODUCT(E48:N48,1/(1+$B92)^(E5:N5)))+((N48*(1+G$88)/($B92-G$88))/(1+$B92)^10)+Assumptions!$B$11)/Assumptions!$B$6 -> 44.245889
B93: =$B$69+(0.02) -> 0.17844056 | C93: =((SUMPRODUCT(E48:N48,1/(1+$B93)^(E5:N5)))+((N48*(1+C$88)/($B93-C$88))/(1+$B93)^10)+Assumptions!$B$11)/Assumptions!$B$6 -> 31.522462 | D93: =((SUMPRODUCT(E48:N48,1/(1+$B93)^(E5:N5)))+((N48*(1+D$88)/($B93-D$88))/(1+$B93)^10)+Assumptions!$B$11)/Assumptions!$B$6 -> 32.912373 | E93: =((SUMPRODUCT(E48:N48,1/(1+$B93)^(E5:N5)))+((N48*(1+E$88)/($B93-E$88))/(1+$B93)^10)+Assumptions!$B$11)/Assumptions!$B$6 -> 34.518711 | F93: =((SUMPRODUCT(E48:N48,1/(1+$B93)^(E5:N5)))+((N48*(1+F$88)/($B93-F$88))/(1+$B93)^10)+Assumptions!$B$11)/Assumptions!$B$6 -> 36.396298 | G93: =((SUMPRODUCT(E48:N48,1/(1+$B93)^(E5:N5)))+((N48*(1+G$88)/($B93-G$88))/(1+$B93)^10)+Assumptions!$B$11)/Assumptions!$B$6 -> 38.620173
A95: SECTION 7 - REVERSE DCF (Base Case WACC/TGR; solves what the market is pricing in)
A96: Equity Value implied by CMP | B96: =Assumptions!$B$5*Assumptions!$B$6 -> 275995.8
A97: EV implied by CMP (less Net Cash) | B97: =B96-Assumptions!$B$11 -> 274472.8
A98: Less: PV of 10Y Explicit FCFFs (Base case) | B98: =C77 -> 14344.769
A99: Net: PV (Terminal Value) implied by CMP | B99: =B97-B98 -> 260128.03
A100: Implied Terminal Value (undiscounted) | B100: =B99*(1+$B$69)^10 -> 1132204.1
A101: Implied Terminal FCFF (at Base WACC & TGR) | B101: =B100*($B$69-C74)/(1+C74) -> 116930.33
A102: vs. Explicit Base-Case Terminal FCFF (FY36E) | B102: =C73 -> 12055.856
A103: Implied vs Explicit Terminal FCFF - Gap % | B103: =B101/B102-1 -> 8.6990478
A104: Base-Case Steady-State FCFF Margin (FY36E FCFF / Revenue) | B104: =N48/N14 -> 0.059969136
A105: Implied Steady-State Revenue (at CMP) | B105: =B101/B104 -> 1949841.7
A106: vs. Explicit Base-Case Revenue (FY36E) | B106: =N14 -> 201034.35
A107: Note: gap > 0 implies market is pricing in a higher terminal cash-generation capacity than the Base-case explicit forecast (i.e. CMP embeds more optimistic long-run assumptions); gap < 0 implies the reverse.
